diodem/__init__.py
diodem/_src.py
diodem/dataverse_github.py
diodem/dataverse_response.json
diodem/test_dataverse_github.py
diodem/test_src.py
diodem/test_utils.py
diodem/utils.py
imt_diodem-1.1.10.dist-info/METADATA
imt_diodem-1.1.10.dist-info/WHEEL
imt_diodem-1.1.10.dist-info/top_level.txt
imt_diodem-1.1.10.dist-info/RECORD
