Metadata-Version: 2.4
Name: imt-diodem
Version: 1.1.10
Summary: DIODEM -- A Diverse Inertial and Optical Dataset of kinEmatic chain Motion
Author-email: Simon Bachhuber <simon.bachhuber@fau.de>
Project-URL: Homepage, https://github.com/SimiPixel/diodem
Project-URL: Issues, https://github.com/SimiPixel/diodem/issues
Classifier: Programming Language :: Python :: 3
Classifier: License :: OSI Approved :: MIT License
Classifier: Operating System :: OS Independent
Requires-Python: >=3.10
Requires-Dist: numpy
Requires-Dist: qmt
Requires-Dist: scipy
Requires-Dist: dm-tree
Requires-Dist: requests
Requires-Dist: pandas
Requires-Dist: imt-tree-utils
